onnx_shrink_ray/__init__.py
onnx_shrink_ray/shrink.py
onnx_shrink_ray-0.0.9.dist-info/licenses/LICENSE
onnx_shrink_ray-0.0.9.dist-info/METADATA
onnx_shrink_ray-0.0.9.dist-info/WHEEL
onnx_shrink_ray-0.0.9.dist-info/top_level.txt
onnx_shrink_ray-0.0.9.dist-info/RECORD
