Metadata-Version: 2.4
Name: onnx_shrink_ray
Version: 0.0.9
Summary: Shrinks the size of ONNX files by quantizing large float constants into eight bit equivalents, while leaving all calculations in floating point.
Author-email: Pete Warden <pete@petewarden.com>
Project-URL: Homepage, https://github.com/usefulsensors/onnx_shrink_ray
Project-URL: Issues, https://github.com/usefulsensors/onnx_shrink_ray/issues
Classifier: Programming Language :: Python :: 3
Classifier: Operating System :: OS Independent
Requires-Python: >=3.8
License-File: LICENSE
Requires-Dist: numpy
Requires-Dist: onnx
Requires-Dist: onnx_graphsurgeon
Requires-Dist: onnxruntime
Dynamic: license-file
